{
  "quotes": {
    "NVDA": {
      "data": {
        "name": "NVIDIA Corporation",
        "price": 202.05999755859375,
        "previousClose": 201.0,
        "currency": "USD",
        "change": 0.53,
        "sector": "Technology",
        "quoteType": "EQUITY",
        "source": "yfinance"
      },
      "ts": 1776721471.7144551
    },
    "AAPL": {
      "data": {
        "name": "Apple Inc.",
        "price": 273.04998779296875,
        "previousClose": 270.6,
        "currency": "USD",
        "change": 0.91,
        "sector": "Technology",
        "quoteType": "EQUITY",
        "source": "yfinance"
      },
      "ts": 1776721461.9980338
    },
    "TSLA": {
      "data": {
        "name": "Tesla, Inc.",
        "price": 392.5,
        "previousClose": 401.05,
        "currency": "USD",
        "change": -2.13,
        "sector": "Consumer Cyclical",
        "quoteType": "EQUITY",
        "source": "yfinance"
      },
      "ts": 1776721477.7906353
    },
    "MSFT": {
      "data": {
        "name": "Microsoft Corporation",
        "price": 418.07000732421875,
        "previousClose": 422.36,
        "currency": "USD",
        "change": -1.02,
        "sector": "Technology",
        "quoteType": "EQUITY",
        "source": "yfinance"
      },
      "ts": 1776721470.2290668
    },
    "GOOGL": {
      "data": {
        "name": "Alphabet Inc.",
        "price": 337.4200134277344,
        "previousClose": 340.55,
        "currency": "USD",
        "change": -0.92,
        "sector": "Communication Services",
        "quoteType": "EQUITY",
        "source": "yfinance"
      },
      "ts": 1776721467.5088465
    },
    "AMZN": {
      "data": {
        "name": "Amazon.com, Inc.",
        "price": 248.27999877929688,
        "previousClose": 250.67,
        "currency": "USD",
        "change": -0.95,
        "sector": "Consumer Cyclical",
        "quoteType": "EQUITY",
        "source": "yfinance"
      },
      "ts": 1776721464.8410485
    },
    "META": {
      "data": {
        "name": "Meta Platforms, Inc.",
        "price": 670.9099731445312,
        "previousClose": 686.8069,
        "currency": "USD",
        "change": -2.31,
        "sector": "Communication Services",
        "quoteType": "EQUITY",
        "source": "yfinance"
      },
      "ts": 1776721468.8177335
    },
    "TSM": {
      "data": {
        "name": "Taiwan Semiconductor Manufactur",
        "price": 366.239990234375,
        "previousClose": 369.3,
        "currency": "USD",
        "change": -0.83,
        "sector": "Technology",
        "quoteType": "EQUITY",
        "source": "yfinance"
      },
      "ts": 1776721479.6397462
    },
    "AMD": {
      "data": {
        "name": "Advanced Micro Devices, Inc.",
        "price": 274.95001220703125,
        "previousClose": 277.25,
        "currency": "USD",
        "change": -0.83,
        "sector": "Technology",
        "quoteType": "EQUITY",
        "source": "yfinance"
      },
      "ts": 1776721463.4043462
    },
    "AVGO": {
      "data": {
        "name": "Broadcom Inc.",
        "price": 399.6300048828125,
        "previousClose": 406.04,
        "currency": "USD",
        "change": -1.58,
        "sector": "Technology",
        "quoteType": "EQUITY",
        "source": "yfinance"
      },
      "ts": 1776721466.2295527
    },
    "2330.TW": {
      "data": {
        "name": "TAIWAN SEMICONDUCTOR MANUFACTUR",
        "price": 2025.0,
        "previousClose": 2085.0,
        "currency": "TWD",
        "change": -2.88,
        "sector": "Technology",
        "quoteType": "EQUITY",
        "source": "yfinance"
      },
      "ts": 1776721460.2742507
    },
    "QQQ": {
      "data": {
        "name": "Invesco QQQ Trust, Series 1",
        "price": 646.7899780273438,
        "previousClose": 648.85,
        "currency": "USD",
        "change": -0.32,
        "sector": "",
        "quoteType": "ETF",
        "source": "yfinance"
      },
      "ts": 1776721476.3198848
    },
    "OPEN": {
      "data": {
        "name": "Opendoor Technologies Inc",
        "price": 5.349999904632568,
        "previousClose": 5.24,
        "currency": "USD",
        "change": 2.1,
        "sector": "Real Estate",
        "quoteType": "EQUITY",
        "source": "yfinance"
      },
      "ts": 1776721474.64348
    },
    "ONDS": {
      "data": {
        "name": "Ondas Inc",
        "price": 10.729999542236328,
        "previousClose": 9.98,
        "currency": "USD",
        "change": 7.52,
        "sector": "Technology",
        "quoteType": "EQUITY",
        "source": "yfinance"
      },
      "ts": 1776721473.2934358
    },
    "VOO": {
      "data": {
        "name": "Vanguard S&P 500 ETF",
        "price": 651.5399780273438,
        "previousClose": 653.389,
        "currency": "USD",
        "change": -0.28,
        "sector": "",
        "quoteType": "ETF",
        "source": "yfinance"
      },
      "ts": 1776721480.9718645
    }
  },
  "history": {
    "2330.TW:5d": {
      "data": {
        "dates": [
          "04/14",
          "04/15",
          "04/16",
          "04/17",
          "04/20"
        ],
        "prices": [
          2055.0,
          2080.0,
          2085.0,
          2030.0,
          2025.0
        ]
      },
      "ts": 1776721482.3714168
    },
    "2330.TW:1mo": {
      "data": {
        "dates": [
          "03/20",
          "03/23",
          "03/24",
          "03/25",
          "03/26",
          "03/27",
          "03/30",
          "03/31",
          "04/01",
          "04/02",
          "04/07",
          "04/08",
          "04/09",
          "04/10",
          "04/13",
          "04/14",
          "04/15",
          "04/16",
          "04/17",
          "04/20"
        ],
        "prices": [
          1840.0,
          1810.0,
          1810.0,
          1845.0,
          1840.0,
          1820.0,
          1780.0,
          1760.0,
          1855.0,
          1810.0,
          1860.0,
          1950.0,
          1955.0,
          2000.0,
          1990.0,
          2055.0,
          2080.0,
          2085.0,
          2030.0,
          2025.0
        ]
      },
      "ts": 1776721482.729235
    },
    "AAPL:1d": {
      "data": {
        "dates": [
          "09:30",
          "09:35",
          "09:40",
          "09:45",
          "09:50",
          "09:55",
          "10:00",
          "10:05",
          "10:10",
          "10:15",
          "10:20",
          "10:25",
          "10:30",
          "10:35",
          "10:40",
          "10:45",
          "10:50",
          "10:55",
          "11:00",
          "11:05",
          "11:10",
          "11:15",
          "11:20",
          "11:25",
          "11:30",
          "11:35",
          "11:40",
          "11:45",
          "11:50",
          "11:55",
          "12:00",
          "12:05",
          "12:10",
          "12:15",
          "12:20",
          "12:25",
          "12:30",
          "12:35",
          "12:40",
          "12:45",
          "12:50",
          "12:55",
          "13:00",
          "13:05",
          "13:10",
          "13:15",
          "13:20",
          "13:25",
          "13:30",
          "13:35",
          "13:40",
          "13:45",
          "13:50",
          "13:55",
          "14:00",
          "14:05",
          "14:10",
          "14:15",
          "14:20",
          "14:25",
          "14:30",
          "14:35",
          "14:40",
          "14:45",
          "14:50",
          "14:55",
          "15:00",
          "15:05",
          "15:10",
          "15:15",
          "15:20",
          "15:25",
          "15:30",
          "15:35",
          "15:40",
          "15:45",
          "15:50",
          "15:55"
        ],
        "prices": [
          272.43,
          272.5,
          272.45,
          272.45,
          273.64,
          273.92,
          273.92,
          273.75,
          273.48,
          273.6,
          274.17,
          273.38,
          273.09,
          273.07,
          272.67,
          273.15,
          272.64,
          272.4,
          271.98,
          271.88,
          271.97,
          272.0,
          272.5,
          272.88,
          272.3,
          272.55,
          272.36,
          272.31,
          272.46,
          272.78,
          272.55,
          272.43,
          272.27,
          272.56,
          272.4,
          272.57,
          273.11,
          272.81,
          272.83,
          272.64,
          272.63,
          272.35,
          271.85,
          271.98,
          272.31,
          272.57,
          272.42,
          272.19,
          272.2,
          272.52,
          272.55,
          272.63,
          272.92,
          272.96,
          272.9,
          273.34,
          273.49,
          273.54,
          273.58,
          273.45,
          273.3,
          273.34,
          273.08,
          273.11,
          273.15,
          272.99,
          273.04,
          273.0,
          273.14,
          273.2,
          273.14,
          272.69,
          272.48,
          272.42,
          272.55,
          272.39,
          272.76,
          272.93
        ]
      },
      "ts": 1776721483.101045
    },
    "AAPL:5d": {
      "data": {
        "dates": [
          "04/14",
          "04/15",
          "04/16",
          "04/17",
          "04/20"
        ],
        "prices": [
          258.83,
          266.43,
          263.4,
          270.23,
          273.05
        ]
      },
      "ts": 1776721483.4912386
    },
    "AAPL:1mo": {
      "data": {
        "dates": [
          "03/23",
          "03/24",
          "03/25",
          "03/26",
          "03/27",
          "03/30",
          "03/31",
          "04/01",
          "04/02",
          "04/06",
          "04/07",
          "04/08",
          "04/09",
          "04/10",
          "04/13",
          "04/14",
          "04/15",
          "04/16",
          "04/17",
          "04/20"
        ],
        "prices": [
          251.49,
          251.64,
          252.62,
          252.89,
          248.8,
          246.63,
          253.79,
          255.63,
          255.92,
          258.86,
          253.5,
          258.9,
          260.49,
          260.48,
          259.2,
          258.83,
          266.43,
          263.4,
          270.23,
          273.05
        ]
      },
      "ts": 1776721483.8739893
    },
    "AMD:1d": {
      "data": {
        "dates": [
          "09:30",
          "09:35",
          "09:40",
          "09:45",
          "09:50",
          "09:55",
          "10:00",
          "10:05",
          "10:10",
          "10:15",
          "10:20",
          "10:25",
          "10:30",
          "10:35",
          "10:40",
          "10:45",
          "10:50",
          "10:55",
          "11:00",
          "11:05",
          "11:10",
          "11:15",
          "11:20",
          "11:25",
          "11:30",
          "11:35",
          "11:40",
          "11:45",
          "11:50",
          "11:55",
          "12:00",
          "12:05",
          "12:10",
          "12:15",
          "12:20",
          "12:25",
          "12:30",
          "12:35",
          "12:40",
          "12:45",
          "12:50",
          "12:55",
          "13:00",
          "13:05",
          "13:10",
          "13:15",
          "13:20",
          "13:25",
          "13:30",
          "13:35",
          "13:40",
          "13:45",
          "13:50",
          "13:55",
          "14:00",
          "14:05",
          "14:10",
          "14:15",
          "14:20",
          "14:25",
          "14:30",
          "14:35",
          "14:40",
          "14:45",
          "14:50",
          "14:55",
          "15:00",
          "15:05",
          "15:10",
          "15:15",
          "15:20",
          "15:25",
          "15:30",
          "15:35",
          "15:40",
          "15:45",
          "15:50",
          "15:55"
        ],
        "prices": [
          285.05,
          282.49,
          282.54,
          279.85,
          281.69,
          279.6,
          277.42,
          276.1,
          277.3,
          275.35,
          276.5,
          276.67,
          276.87,
          277.62,
          276.72,
          276.5,
          275.33,
          274.33,
          273.66,
          273.83,
          274.45,
          274.59,
          275.28,
          275.8,
          274.77,
          274.83,
          274.67,
          275.22,
          274.79,
          274.61,
          274.77,
          274.78,
          275.02,
          274.85,
          274.44,
          274.11,
          274.18,
          273.85,
          274.29,
          273.34,
          273.59,
          273.67,
          273.8,
          273.71,
          273.64,
          273.71,
          273.46,
          272.97,
          273.44,
          273.61,
          273.4,
          273.7,
          274.17,
          274.05,
          274.2,
          273.86,
          273.52,
          273.47,
          273.64,
          274.35,
          274.75,
          274.44,
          274.98,
          275.0,
          275.79,
          276.12,
          276.02,
          276.13,
          275.74,
          275.7,
          275.05,
          275.53,
          275.25,
          275.54,
          275.04,
          275.3,
          274.49,
          274.96
        ]
      },
      "ts": 1776721484.2201912
    },
    "AMD:5d": {
      "data": {
        "dates": [
          "04/14",
          "04/15",
          "04/16",
          "04/17",
          "04/20"
        ],
        "prices": [
          255.07,
          258.12,
          278.26,
          278.39,
          274.95
        ]
      },
      "ts": 1776721484.603796
    },
    "AMD:1mo": {
      "data": {
        "dates": [
          "03/23",
          "03/24",
          "03/25",
          "03/26",
          "03/27",
          "03/30",
          "03/31",
          "04/01",
          "04/02",
          "04/06",
          "04/07",
          "04/08",
          "04/09",
          "04/10",
          "04/13",
          "04/14",
          "04/15",
          "04/16",
          "04/17",
          "04/20"
        ],
        "prices": [
          202.68,
          205.37,
          220.27,
          203.77,
          201.99,
          196.04,
          203.43,
          210.21,
          217.5,
          220.18,
          221.53,
          231.82,
          236.64,
          245.04,
          246.83,
          255.07,
          258.12,
          278.26,
          278.39,
          274.95
        ]
      },
      "ts": 1776721485.019104
    },
    "AMZN:1d": {
      "data": {
        "dates": [
          "09:30",
          "09:35",
          "09:40",
          "09:45",
          "09:50",
          "09:55",
          "10:00",
          "10:05",
          "10:10",
          "10:15",
          "10:20",
          "10:25",
          "10:30",
          "10:35",
          "10:40",
          "10:45",
          "10:50",
          "10:55",
          "11:00",
          "11:05",
          "11:10",
          "11:15",
          "11:20",
          "11:25",
          "11:30",
          "11:35",
          "11:40",
          "11:45",
          "11:50",
          "11:55",
          "12:00",
          "12:05",
          "12:10",
          "12:15",
          "12:20",
          "12:25",
          "12:30",
          "12:35",
          "12:40",
          "12:45",
          "12:50",
          "12:55",
          "13:00",
          "13:05",
          "13:10",
          "13:15",
          "13:20",
          "13:25",
          "13:30",
          "13:35",
          "13:40",
          "13:45",
          "13:50",
          "13:55",
          "14:00",
          "14:05",
          "14:10",
          "14:15",
          "14:20",
          "14:25",
          "14:30",
          "14:35",
          "14:40",
          "14:45",
          "14:50",
          "14:55",
          "15:00",
          "15:05",
          "15:10",
          "15:15",
          "15:20",
          "15:25",
          "15:30",
          "15:35",
          "15:40",
          "15:45",
          "15:50",
          "15:55"
        ],
        "prices": [
          248.99,
          247.67,
          247.24,
          247.07,
          247.33,
          247.67,
          246.92,
          247.27,
          247.88,
          247.2,
          247.43,
          247.17,
          247.15,
          247.1,
          246.63,
          246.92,
          246.25,
          245.79,
          245.74,
          245.65,
          245.99,
          246.04,
          246.11,
          247.02,
          246.22,
          246.33,
          246.42,
          246.65,
          246.58,
          246.79,
          246.68,
          246.83,
          246.92,
          246.87,
          246.7,
          246.77,
          247.14,
          246.91,
          247.09,
          246.95,
          247.23,
          247.35,
          247.35,
          247.52,
          247.44,
          247.55,
          247.56,
          247.61,
          247.35,
          247.33,
          247.34,
          247.4,
          247.69,
          247.51,
          247.65,
          247.93,
          247.84,
          247.91,
          248.1,
          247.8,
          247.87,
          247.96,
          248.17,
          248.26,
          248.37,
          248.08,
          248.17,
          248.27,
          248.26,
          248.16,
          247.9,
          248.14,
          248.43,
          248.44,
          248.42,
          248.32,
          247.99,
          248.29
        ]
      },
      "ts": 1776721485.3664258
    },
    "AMZN:5d": {
      "data": {
        "dates": [
          "04/14",
          "04/15",
          "04/16",
          "04/17",
          "04/20"
        ],
        "prices": [
          249.02,
          248.5,
          249.7,
          250.56,
          248.28
        ]
      },
      "ts": 1776721485.7367566
    },
    "AMZN:1mo": {
      "data": {
        "dates": [
          "03/23",
          "03/24",
          "03/25",
          "03/26",
          "03/27",
          "03/30",
          "03/31",
          "04/01",
          "04/02",
          "04/06",
          "04/07",
          "04/08",
          "04/09",
          "04/10",
          "04/13",
          "04/14",
          "04/15",
          "04/16",
          "04/17",
          "04/20"
        ],
        "prices": [
          210.14,
          207.24,
          211.71,
          207.54,
          199.34,
          200.95,
          208.27,
          210.57,
          209.77,
          212.79,
          213.77,
          221.25,
          233.65,
          238.38,
          239.89,
          249.02,
          248.5,
          249.7,
          250.56,
          248.28
        ]
      },
      "ts": 1776721486.0719128
    },
    "AVGO:1d": {
      "data": {
        "dates": [
          "09:30",
          "09:35",
          "09:40",
          "09:45",
          "09:50",
          "09:55",
          "10:00",
          "10:05",
          "10:10",
          "10:15",
          "10:20",
          "10:25",
          "10:30",
          "10:35",
          "10:40",
          "10:45",
          "10:50",
          "10:55",
          "11:00",
          "11:05",
          "11:10",
          "11:15",
          "11:20",
          "11:25",
          "11:30",
          "11:35",
          "11:40",
          "11:45",
          "11:50",
          "11:55",
          "12:00",
          "12:05",
          "12:10",
          "12:15",
          "12:20",
          "12:25",
          "12:30",
          "12:35",
          "12:40",
          "12:45",
          "12:50",
          "12:55",
          "13:00",
          "13:05",
          "13:10",
          "13:15",
          "13:20",
          "13:25",
          "13:30",
          "13:35",
          "13:40",
          "13:45",
          "13:50",
          "13:55",
          "14:00",
          "14:05",
          "14:10",
          "14:15",
          "14:20",
          "14:25",
          "14:30",
          "14:35",
          "14:40",
          "14:45",
          "14:50",
          "14:55",
          "15:00",
          "15:05",
          "15:10",
          "15:15",
          "15:20",
          "15:25",
          "15:30",
          "15:35",
          "15:40",
          "15:45",
          "15:50",
          "15:55"
        ],
        "prices": [
          403.45,
          401.91,
          403.01,
          401.83,
          402.27,
          402.05,
          400.1,
          399.95,
          400.15,
          398.87,
          399.51,
          399.27,
          399.68,
          400.16,
          399.36,
          399.59,
          399.06,
          397.9,
          397.88,
          397.2,
          396.55,
          397.58,
          397.8,
          398.33,
          397.88,
          398.15,
          397.08,
          397.02,
          397.01,
          397.08,
          396.92,
          397.47,
          397.88,
          397.99,
          397.9,
          397.67,
          397.99,
          397.99,
          397.92,
          397.5,
          397.3,
          397.43,
          397.61,
          397.4,
          396.84,
          397.31,
          397.36,
          397.03,
          396.58,
          396.75,
          397.03,
          397.22,
          397.15,
          396.92,
          396.87,
          396.85,
          396.48,
          396.62,
          396.89,
          397.07,
          396.86,
          396.78,
          397.83,
          398.38,
          397.98,
          398.27,
          398.4,
          398.82,
          398.9,
          398.65,
          398.96,
          398.92,
          398.54,
          399.09,
          398.92,
          398.77,
          398.67,
          399.84
        ]
      },
      "ts": 1776721486.4159875
    },
    "AVGO:5d": {
      "data": {
        "dates": [
          "04/14",
          "04/15",
          "04/16",
          "04/17",
          "04/20"
        ],
        "prices": [
          380.78,
          396.72,
          398.47,
          406.54,
          399.63
        ]
      },
      "ts": 1776721486.8111832
    },
    "AVGO:1mo": {
      "data": {
        "dates": [
          "03/23",
          "03/24",
          "03/25",
          "03/26",
          "03/27",
          "03/30",
          "03/31",
          "04/01",
          "04/02",
          "04/06",
          "04/07",
          "04/08",
          "04/09",
          "04/10",
          "04/13",
          "04/14",
          "04/15",
          "04/16",
          "04/17",
          "04/20"
        ],
        "prices": [
          322.51,
          318.29,
          318.81,
          309.42,
          300.68,
          293.41,
          309.51,
          313.49,
          314.55,
          314.43,
          333.97,
          350.63,
          354.91,
          371.55,
          379.75,
          380.78,
          396.72,
          398.47,
          406.54,
          399.63
        ]
      },
      "ts": 1776721487.1717355
    },
    "GOOGL:1d": {
      "data": {
        "dates": [
          "09:30",
          "09:35",
          "09:40",
          "09:45",
          "09:50",
          "09:55",
          "10:00",
          "10:05",
          "10:10",
          "10:15",
          "10:20",
          "10:25",
          "10:30",
          "10:35",
          "10:40",
          "10:45",
          "10:50",
          "10:55",
          "11:00",
          "11:05",
          "11:10",
          "11:15",
          "11:20",
          "11:25",
          "11:30",
          "11:35",
          "11:40",
          "11:45",
          "11:50",
          "11:55",
          "12:00",
          "12:05",
          "12:10",
          "12:15",
          "12:20",
          "12:25",
          "12:30",
          "12:35",
          "12:40",
          "12:45",
          "12:50",
          "12:55",
          "13:00",
          "13:05",
          "13:10",
          "13:15",
          "13:20",
          "13:25",
          "13:30",
          "13:35",
          "13:40",
          "13:45",
          "13:50",
          "13:55",
          "14:00",
          "14:05",
          "14:10",
          "14:15",
          "14:20",
          "14:25",
          "14:30",
          "14:35",
          "14:40",
          "14:45",
          "14:50",
          "14:55",
          "15:00",
          "15:05",
          "15:10",
          "15:15",
          "15:20",
          "15:25",
          "15:30",
          "15:35",
          "15:40",
          "15:45",
          "15:50",
          "15:55"
        ],
        "prices": [
          339.83,
          338.93,
          339.03,
          338.55,
          339.48,
          340.05,
          339.06,
          339.1,
          339.51,
          339.48,
          339.79,
          339.7,
          339.47,
          339.33,
          339.0,
          339.44,
          338.83,
          338.32,
          337.33,
          337.24,
          337.19,
          337.42,
          338.32,
          339.07,
          338.58,
          338.21,
          338.44,
          338.55,
          338.15,
          338.26,
          338.27,
          338.71,
          338.9,
          338.97,
          338.77,
          338.7,
          339.02,
          339.05,
          339.21,
          339.04,
          338.91,
          338.86,
          338.62,
          338.49,
          338.46,
          338.73,
          338.59,
          338.27,
          338.16,
          338.54,
          338.69,
          338.83,
          338.79,
          338.22,
          338.14,
          338.51,
          338.49,
          338.44,
          338.54,
          338.36,
          338.43,
          338.39,
          338.56,
          338.7,
          338.74,
          338.33,
          338.21,
          338.41,
          338.63,
          338.52,
          338.43,
          338.36,
          338.08,
          337.95,
          337.55,
          337.58,
          337.51,
          337.39
        ]
      },
      "ts": 1776721487.524388
    },
    "GOOGL:5d": {
      "data": {
        "dates": [
          "04/14",
          "04/15",
          "04/16",
          "04/17",
          "04/20"
        ],
        "prices": [
          332.91,
          337.12,
          336.02,
          341.68,
          337.42
        ]
      },
      "ts": 1776721487.8723397
    },
    "GOOGL:1mo": {
      "data": {
        "dates": [
          "03/23",
          "03/24",
          "03/25",
          "03/26",
          "03/27",
          "03/30",
          "03/31",
          "04/01",
          "04/02",
          "04/06",
          "04/07",
          "04/08",
          "04/09",
          "04/10",
          "04/13",
          "04/14",
          "04/15",
          "04/16",
          "04/17",
          "04/20"
        ],
        "prices": [
          302.06,
          290.44,
          290.93,
          280.92,
          274.34,
          273.5,
          287.56,
          297.39,
          295.77,
          299.99,
          305.46,
          317.32,
          318.49,
          317.24,
          321.31,
          332.91,
          337.12,
          336.02,
          341.68,
          337.42
        ]
      },
      "ts": 1776721488.2554321
    },
    "META:1d": {
      "data": {
        "dates": [
          "09:30",
          "09:35",
          "09:40",
          "09:45",
          "09:50",
          "09:55",
          "10:00",
          "10:05",
          "10:10",
          "10:15",
          "10:20",
          "10:25",
          "10:30",
          "10:35",
          "10:40",
          "10:45",
          "10:50",
          "10:55",
          "11:00",
          "11:05",
          "11:10",
          "11:15",
          "11:20",
          "11:25",
          "11:30",
          "11:35",
          "11:40",
          "11:45",
          "11:50",
          "11:55",
          "12:00",
          "12:05",
          "12:10",
          "12:15",
          "12:20",
          "12:25",
          "12:30",
          "12:35",
          "12:40",
          "12:45",
          "12:50",
          "12:55",
          "13:00",
          "13:05",
          "13:10",
          "13:15",
          "13:20",
          "13:25",
          "13:30",
          "13:35",
          "13:40",
          "13:45",
          "13:50",
          "13:55",
          "14:00",
          "14:05",
          "14:10",
          "14:15",
          "14:20",
          "14:25",
          "14:30",
          "14:35",
          "14:40",
          "14:45",
          "14:50",
          "14:55",
          "15:00",
          "15:05",
          "15:10",
          "15:15",
          "15:20",
          "15:25",
          "15:30",
          "15:35",
          "15:40",
          "15:45",
          "15:50",
          "15:55"
        ],
        "prices": [
          681.55,
          674.54,
          676.71,
          672.87,
          675.95,
          677.52,
          676.36,
          677.14,
          676.8,
          677.22,
          677.85,
          676.08,
          676.54,
          675.85,
          673.43,
          673.53,
          670.9,
          670.21,
          668.89,
          669.56,
          671.11,
          671.7,
          672.15,
          673.57,
          672.59,
          673.62,
          673.46,
          673.88,
          672.13,
          672.84,
          672.45,
          673.27,
          673.5,
          673.36,
          673.03,
          672.83,
          673.33,
          672.6,
          673.09,
          672.58,
          672.03,
          671.78,
          671.69,
          672.47,
          672.9,
          673.42,
          673.05,
          672.65,
          671.91,
          672.47,
          672.26,
          672.8,
          672.55,
          671.2,
          671.82,
          672.7,
          672.6,
          672.72,
          673.03,
          672.65,
          672.42,
          671.99,
          671.76,
          671.76,
          671.75,
          670.82,
          670.66,
          670.09,
          670.73,
          670.68,
          671.22,
          670.71,
          672.06,
          671.74,
          671.32,
          671.46,
          670.74,
          670.95
        ]
      },
      "ts": 1776721488.6307507
    },
    "META:5d": {
      "data": {
        "dates": [
          "04/14",
          "04/15",
          "04/16",
          "04/17",
          "04/20"
        ],
        "prices": [
          662.49,
          671.58,
          676.87,
          688.55,
          670.91
        ]
      },
      "ts": 1776721488.9705348
    },
    "META:1mo": {
      "data": {
        "dates": [
          "03/23",
          "03/24",
          "03/25",
          "03/26",
          "03/27",
          "03/30",
          "03/31",
          "04/01",
          "04/02",
          "04/06",
          "04/07",
          "04/08",
          "04/09",
          "04/10",
          "04/13",
          "04/14",
          "04/15",
          "04/16",
          "04/17",
          "04/20"
        ],
        "prices": [
          604.06,
          592.92,
          594.89,
          547.54,
          525.72,
          536.38,
          572.13,
          579.23,
          574.46,
          573.02,
          575.05,
          612.42,
          628.39,
          629.86,
          634.53,
          662.49,
          671.58,
          676.87,
          688.55,
          670.91
        ]
      },
      "ts": 1776721489.35066
    },
    "MSFT:1d": {
      "data": {
        "dates": [
          "09:30",
          "09:35",
          "09:40",
          "09:45",
          "09:50",
          "09:55",
          "10:00",
          "10:05",
          "10:10",
          "10:15",
          "10:20",
          "10:25",
          "10:30",
          "10:35",
          "10:40",
          "10:45",
          "10:50",
          "10:55",
          "11:00",
          "11:05",
          "11:10",
          "11:15",
          "11:20",
          "11:25",
          "11:30",
          "11:35",
          "11:40",
          "11:45",
          "11:50",
          "11:55",
          "12:00",
          "12:05",
          "12:10",
          "12:15",
          "12:20",
          "12:25",
          "12:30",
          "12:35",
          "12:40",
          "12:45",
          "12:50",
          "12:55",
          "13:00",
          "13:05",
          "13:10",
          "13:15",
          "13:20",
          "13:25",
          "13:30",
          "13:35",
          "13:40",
          "13:45",
          "13:50",
          "13:55",
          "14:00",
          "14:05",
          "14:10",
          "14:15",
          "14:20",
          "14:25",
          "14:30",
          "14:35",
          "14:40",
          "14:45",
          "14:50",
          "14:55",
          "15:00",
          "15:05",
          "15:10",
          "15:15",
          "15:20",
          "15:25",
          "15:30",
          "15:35",
          "15:40",
          "15:45",
          "15:50",
          "15:55"
        ],
        "prices": [
          420.84,
          418.05,
          417.36,
          418.15,
          419.52,
          420.53,
          421.92,
          422.18,
          421.07,
          419.82,
          420.42,
          419.5,
          419.07,
          419.43,
          418.36,
          419.18,
          418.61,
          418.1,
          417.49,
          417.03,
          417.5,
          417.39,
          417.17,
          418.15,
          416.89,
          417.3,
          417.17,
          417.22,
          417.78,
          417.47,
          417.79,
          417.8,
          418.28,
          418.36,
          418.58,
          418.85,
          418.92,
          419.03,
          419.33,
          419.33,
          419.05,
          418.8,
          418.77,
          419.18,
          419.38,
          419.91,
          419.86,
          419.16,
          418.83,
          418.46,
          418.66,
          418.8,
          418.93,
          418.37,
          418.15,
          418.3,
          418.37,
          418.56,
          418.99,
          418.62,
          418.24,
          417.58,
          417.52,
          417.46,
          417.67,
          416.99,
          417.12,
          417.48,
          417.33,
          417.64,
          417.7,
          417.33,
          417.66,
          417.42,
          417.1,
          417.32,
          417.2,
          418.11
        ]
      },
      "ts": 1776721489.6948717
    },
    "MSFT:5d": {
      "data": {
        "dates": [
          "04/14",
          "04/15",
          "04/16",
          "04/17",
          "04/20"
        ],
        "prices": [
          393.11,
          411.22,
          420.26,
          422.79,
          418.07
        ]
      },
      "ts": 1776721490.145867
    },
    "MSFT:1mo": {
      "data": {
        "dates": [
          "03/23",
          "03/24",
          "03/25",
          "03/26",
          "03/27",
          "03/30",
          "03/31",
          "04/01",
          "04/02",
          "04/06",
          "04/07",
          "04/08",
          "04/09",
          "04/10",
          "04/13",
          "04/14",
          "04/15",
          "04/16",
          "04/17",
          "04/20"
        ],
        "prices": [
          383.0,
          372.74,
          371.04,
          365.97,
          356.77,
          358.96,
          370.17,
          369.37,
          373.46,
          372.88,
          372.29,
          374.33,
          373.07,
          370.87,
          384.37,
          393.11,
          411.22,
          420.26,
          422.79,
          418.07
        ]
      },
      "ts": 1776721490.531571
    },
    "NVDA:1d": {
      "data": {
        "dates": [
          "09:30",
          "09:35",
          "09:40",
          "09:45",
          "09:50",
          "09:55",
          "10:00",
          "10:05",
          "10:10",
          "10:15",
          "10:20",
          "10:25",
          "10:30",
          "10:35",
          "10:40",
          "10:45",
          "10:50",
          "10:55",
          "11:00",
          "11:05",
          "11:10",
          "11:15",
          "11:20",
          "11:25",
          "11:30",
          "11:35",
          "11:40",
          "11:45",
          "11:50",
          "11:55",
          "12:00",
          "12:05",
          "12:10",
          "12:15",
          "12:20",
          "12:25",
          "12:30",
          "12:35",
          "12:40",
          "12:45",
          "12:50",
          "12:55",
          "13:00",
          "13:05",
          "13:10",
          "13:15",
          "13:20",
          "13:25",
          "13:30",
          "13:35",
          "13:40",
          "13:45",
          "13:50",
          "13:55",
          "14:00",
          "14:05",
          "14:10",
          "14:15",
          "14:20",
          "14:25",
          "14:30",
          "14:35",
          "14:40",
          "14:45",
          "14:50",
          "14:55",
          "15:00",
          "15:05",
          "15:10",
          "15:15",
          "15:20",
          "15:25",
          "15:30",
          "15:35",
          "15:40",
          "15:45",
          "15:50",
          "15:55"
        ],
        "prices": [
          200.35,
          199.58,
          199.86,
          199.6,
          199.96,
          200.25,
          199.7,
          199.84,
          199.59,
          199.07,
          199.43,
          199.13,
          199.1,
          199.32,
          199.07,
          199.35,
          198.99,
          198.54,
          198.36,
          198.38,
          198.43,
          198.6,
          198.99,
          199.27,
          198.9,
          199.13,
          198.79,
          198.55,
          198.62,
          198.65,
          198.71,
          199.01,
          199.12,
          199.21,
          199.4,
          199.18,
          199.47,
          199.33,
          199.43,
          199.4,
          199.41,
          199.29,
          199.33,
          199.51,
          199.59,
          199.7,
          199.71,
          199.53,
          199.56,
          199.71,
          199.95,
          200.07,
          200.07,
          199.95,
          200.18,
          200.34,
          200.3,
          200.39,
          200.49,
          200.59,
          200.66,
          200.46,
          200.9,
          200.75,
          200.9,
          200.79,
          200.78,
          200.86,
          201.1,
          201.19,
          201.09,
          201.13,
          201.14,
          201.55,
          201.6,
          201.68,
          202.03,
          202.11
        ]
      },
      "ts": 1776721490.8879554
    },
    "NVDA:5d": {
      "data": {
        "dates": [
          "04/14",
          "04/15",
          "04/16",
          "04/17",
          "04/20"
        ],
        "prices": [
          196.51,
          198.87,
          198.35,
          201.68,
          202.06
        ]
      },
      "ts": 1776721491.3113234
    },
    "NVDA:1mo": {
      "data": {
        "dates": [
          "03/23",
          "03/24",
          "03/25",
          "03/26",
          "03/27",
          "03/30",
          "03/31",
          "04/01",
          "04/02",
          "04/06",
          "04/07",
          "04/08",
          "04/09",
          "04/10",
          "04/13",
          "04/14",
          "04/15",
          "04/16",
          "04/17",
          "04/20"
        ],
        "prices": [
          175.64,
          175.2,
          178.68,
          171.24,
          167.52,
          165.17,
          174.4,
          175.75,
          177.39,
          177.64,
          178.1,
          182.08,
          183.91,
          188.63,
          189.31,
          196.51,
          198.87,
          198.35,
          201.68,
          202.06
        ]
      },
      "ts": 1776721491.677386
    },
    "ONDS:1d": {
      "data": {
        "dates": [
          "09:30",
          "09:35",
          "09:40",
          "09:45",
          "09:50",
          "09:55",
          "10:00",
          "10:05",
          "10:10",
          "10:15",
          "10:20",
          "10:25",
          "10:30",
          "10:35",
          "10:40",
          "10:45",
          "10:50",
          "10:55",
          "11:00",
          "11:05",
          "11:10",
          "11:15",
          "11:20",
          "11:25",
          "11:30",
          "11:35",
          "11:40",
          "11:45",
          "11:50",
          "11:55",
          "12:00",
          "12:05",
          "12:10",
          "12:15",
          "12:20",
          "12:25",
          "12:30",
          "12:35",
          "12:40",
          "12:45",
          "12:50",
          "12:55",
          "13:00",
          "13:05",
          "13:10",
          "13:15",
          "13:20",
          "13:25",
          "13:30",
          "13:35",
          "13:40",
          "13:45",
          "13:50",
          "13:55",
          "14:00",
          "14:05",
          "14:10",
          "14:15",
          "14:20",
          "14:25",
          "14:30",
          "14:35",
          "14:40",
          "14:45",
          "14:50",
          "14:55",
          "15:00",
          "15:05",
          "15:10",
          "15:15",
          "15:20",
          "15:25",
          "15:30",
          "15:35",
          "15:40",
          "15:45",
          "15:50",
          "15:55"
        ],
        "prices": [
          9.89,
          9.99,
          10.13,
          10.05,
          10.2,
          10.44,
          10.55,
          10.56,
          10.59,
          10.51,
          10.7,
          10.61,
          10.5,
          10.57,
          10.59,
          10.77,
          10.65,
          10.64,
          10.56,
          10.56,
          10.74,
          10.8,
          10.93,
          10.93,
          10.88,
          11.01,
          10.99,
          10.95,
          10.92,
          10.86,
          10.75,
          10.76,
          10.68,
          10.67,
          10.62,
          10.61,
          10.68,
          10.63,
          10.63,
          10.63,
          10.59,
          10.59,
          10.58,
          10.63,
          10.72,
          10.69,
          10.68,
          10.69,
          10.69,
          10.69,
          10.68,
          10.65,
          10.62,
          10.61,
          10.64,
          10.7,
          10.74,
          10.77,
          10.82,
          10.85,
          10.88,
          10.81,
          10.86,
          10.91,
          10.98,
          10.98,
          10.88,
          10.86,
          10.9,
          10.88,
          10.86,
          10.86,
          10.81,
          10.83,
          10.72,
          10.69,
          10.69,
          10.72
        ]
      },
      "ts": 1776721492.069911
    },
    "ONDS:5d": {
      "data": {
        "dates": [
          "04/14",
          "04/15",
          "04/16",
          "04/17",
          "04/20"
        ],
        "prices": [
          9.4,
          10.03,
          10.2,
          10.0,
          10.73
        ]
      },
      "ts": 1776721492.4352345
    },
    "ONDS:1mo": {
      "data": {
        "dates": [
          "03/23",
          "03/24",
          "03/25",
          "03/26",
          "03/27",
          "03/30",
          "03/31",
          "04/01",
          "04/02",
          "04/06",
          "04/07",
          "04/08",
          "04/09",
          "04/10",
          "04/13",
          "04/14",
          "04/15",
          "04/16",
          "04/17",
          "04/20"
        ],
        "prices": [
          10.9,
          10.68,
          10.31,
          9.44,
          8.8,
          8.15,
          9.04,
          8.81,
          9.6,
          9.52,
          9.53,
          9.45,
          9.14,
          9.13,
          9.47,
          9.4,
          10.03,
          10.2,
          10.0,
          10.73
        ]
      },
      "ts": 1776721492.8414545
    },
    "OPEN:1d": {
      "data": {
        "dates": [
          "09:30",
          "09:35",
          "09:40",
          "09:45",
          "09:50",
          "09:55",
          "10:00",
          "10:05",
          "10:10",
          "10:15",
          "10:20",
          "10:25",
          "10:30",
          "10:35",
          "10:40",
          "10:45",
          "10:50",
          "10:55",
          "11:00",
          "11:05",
          "11:10",
          "11:15",
          "11:20",
          "11:25",
          "11:30",
          "11:35",
          "11:40",
          "11:45",
          "11:50",
          "11:55",
          "12:00",
          "12:05",
          "12:10",
          "12:15",
          "12:20",
          "12:25",
          "12:30",
          "12:35",
          "12:40",
          "12:45",
          "12:50",
          "12:55",
          "13:00",
          "13:05",
          "13:10",
          "13:15",
          "13:20",
          "13:25",
          "13:30",
          "13:35",
          "13:40",
          "13:45",
          "13:50",
          "13:55",
          "14:00",
          "14:05",
          "14:10",
          "14:15",
          "14:20",
          "14:25",
          "14:30",
          "14:35",
          "14:40",
          "14:45",
          "14:50",
          "14:55",
          "15:00",
          "15:05",
          "15:10",
          "15:15",
          "15:20",
          "15:25",
          "15:30",
          "15:35",
          "15:40",
          "15:45",
          "15:50",
          "15:55"
        ],
        "prices": [
          5.25,
          5.22,
          5.26,
          5.24,
          5.26,
          5.26,
          5.26,
          5.28,
          5.33,
          5.3,
          5.35,
          5.32,
          5.34,
          5.36,
          5.34,
          5.37,
          5.32,
          5.29,
          5.26,
          5.26,
          5.27,
          5.3,
          5.32,
          5.34,
          5.32,
          5.32,
          5.32,
          5.31,
          5.32,
          5.3,
          5.28,
          5.27,
          5.28,
          5.28,
          5.28,
          5.26,
          5.28,
          5.26,
          5.28,
          5.27,
          5.25,
          5.26,
          5.26,
          5.28,
          5.28,
          5.27,
          5.27,
          5.27,
          5.25,
          5.27,
          5.26,
          5.28,
          5.28,
          5.26,
          5.28,
          5.3,
          5.28,
          5.3,
          5.29,
          5.33,
          5.33,
          5.31,
          5.32,
          5.34,
          5.34,
          5.34,
          5.32,
          5.32,
          5.32,
          5.32,
          5.32,
          5.3,
          5.32,
          5.32,
          5.3,
          5.3,
          5.32,
          5.35
        ]
      },
      "ts": 1776721493.2041624
    },
    "OPEN:5d": {
      "data": {
        "dates": [
          "04/14",
          "04/15",
          "04/16",
          "04/17",
          "04/20"
        ],
        "prices": [
          4.51,
          4.82,
          5.27,
          5.29,
          5.35
        ]
      },
      "ts": 1776721493.6098032
    },
    "OPEN:1mo": {
      "data": {
        "dates": [
          "03/23",
          "03/24",
          "03/25",
          "03/26",
          "03/27",
          "03/30",
          "03/31",
          "04/01",
          "04/02",
          "04/06",
          "04/07",
          "04/08",
          "04/09",
          "04/10",
          "04/13",
          "04/14",
          "04/15",
          "04/16",
          "04/17",
          "04/20"
        ],
        "prices": [
          5.21,
          5.18,
          5.1,
          4.9,
          4.8,
          4.43,
          4.68,
          4.57,
          4.74,
          4.61,
          4.55,
          4.64,
          4.31,
          4.32,
          4.36,
          4.51,
          4.82,
          5.27,
          5.29,
          5.35
        ]
      },
      "ts": 1776721493.9749806
    },
    "QQQ:1d": {
      "data": {
        "dates": [
          "09:30",
          "09:35",
          "09:40",
          "09:45",
          "09:50",
          "09:55",
          "10:00",
          "10:05",
          "10:10",
          "10:15",
          "10:20",
          "10:25",
          "10:30",
          "10:35",
          "10:40",
          "10:45",
          "10:50",
          "10:55",
          "11:00",
          "11:05",
          "11:10",
          "11:15",
          "11:20",
          "11:25",
          "11:30",
          "11:35",
          "11:40",
          "11:45",
          "11:50",
          "11:55",
          "12:00",
          "12:05",
          "12:10",
          "12:15",
          "12:20",
          "12:25",
          "12:30",
          "12:35",
          "12:40",
          "12:45",
          "12:50",
          "12:55",
          "13:00",
          "13:05",
          "13:10",
          "13:15",
          "13:20",
          "13:25",
          "13:30",
          "13:35",
          "13:40",
          "13:45",
          "13:50",
          "13:55",
          "14:00",
          "14:05",
          "14:10",
          "14:15",
          "14:20",
          "14:25",
          "14:30",
          "14:35",
          "14:40",
          "14:45",
          "14:50",
          "14:55",
          "15:00",
          "15:05",
          "15:10",
          "15:15",
          "15:20",
          "15:25",
          "15:30",
          "15:35",
          "15:40",
          "15:45",
          "15:50",
          "15:55"
        ],
        "prices": [
          648.39,
          646.83,
          646.89,
          646.44,
          647.49,
          647.66,
          646.83,
          647.27,
          647.07,
          646.46,
          647.28,
          646.41,
          646.35,
          646.38,
          645.6,
          646.06,
          645.03,
          644.15,
          643.43,
          643.31,
          643.77,
          644.16,
          644.88,
          645.65,
          644.68,
          644.87,
          644.61,
          644.58,
          644.58,
          644.68,
          644.36,
          644.83,
          645.12,
          645.18,
          645.1,
          645.08,
          645.42,
          645.05,
          645.34,
          645.28,
          645.35,
          645.17,
          645.05,
          645.41,
          645.59,
          645.93,
          645.91,
          645.61,
          645.44,
          645.76,
          645.89,
          646.17,
          646.28,
          645.86,
          645.93,
          646.33,
          646.26,
          646.41,
          646.64,
          646.49,
          646.44,
          646.01,
          646.3,
          646.5,
          646.76,
          646.43,
          646.41,
          646.51,
          646.61,
          646.55,
          646.39,
          646.33,
          646.22,
          646.38,
          646.17,
          646.27,
          646.33,
          646.77
        ]
      },
      "ts": 1776721494.3729408
    },
    "QQQ:5d": {
      "data": {
        "dates": [
          "04/14",
          "04/15",
          "04/16",
          "04/17",
          "04/20"
        ],
        "prices": [
          628.6,
          637.4,
          640.47,
          648.85,
          646.79
        ]
      },
      "ts": 1776721494.7995684
    },
    "QQQ:1mo": {
      "data": {
        "dates": [
          "03/23",
          "03/24",
          "03/25",
          "03/26",
          "03/27",
          "03/30",
          "03/31",
          "04/01",
          "04/02",
          "04/06",
          "04/07",
          "04/08",
          "04/09",
          "04/10",
          "04/13",
          "04/14",
          "04/15",
          "04/16",
          "04/17",
          "04/20"
        ],
        "prices": [
          588.0,
          583.98,
          587.82,
          573.79,
          562.58,
          558.28,
          577.18,
          584.31,
          584.98,
          588.5,
          588.59,
          606.09,
          610.19,
          611.07,
          617.39,
          628.6,
          637.4,
          640.47,
          648.85,
          646.79
        ]
      },
      "ts": 1776721495.206858
    },
    "TSLA:1d": {
      "data": {
        "dates": [
          "09:30",
          "09:35",
          "09:40",
          "09:45",
          "09:50",
          "09:55",
          "10:00",
          "10:05",
          "10:10",
          "10:15",
          "10:20",
          "10:25",
          "10:30",
          "10:35",
          "10:40",
          "10:45",
          "10:50",
          "10:55",
          "11:00",
          "11:05",
          "11:10",
          "11:15",
          "11:20",
          "11:25",
          "11:30",
          "11:35",
          "11:40",
          "11:45",
          "11:50",
          "11:55",
          "12:00",
          "12:05",
          "12:10",
          "12:15",
          "12:20",
          "12:25",
          "12:30",
          "12:35",
          "12:40",
          "12:45",
          "12:50",
          "12:55",
          "13:00",
          "13:05",
          "13:10",
          "13:15",
          "13:20",
          "13:25",
          "13:30",
          "13:35",
          "13:40",
          "13:45",
          "13:50",
          "13:55",
          "14:00",
          "14:05",
          "14:10",
          "14:15",
          "14:20",
          "14:25",
          "14:30",
          "14:35",
          "14:40",
          "14:45",
          "14:50",
          "14:55",
          "15:00",
          "15:05",
          "15:10",
          "15:15",
          "15:20",
          "15:25",
          "15:30",
          "15:35",
          "15:40",
          "15:45",
          "15:50",
          "15:55"
        ],
        "prices": [
          404.82,
          399.8,
          395.59,
          394.48,
          396.38,
          395.8,
          394.91,
          395.8,
          393.39,
          393.04,
          394.33,
          392.99,
          393.3,
          394.03,
          392.65,
          392.96,
          391.57,
          390.37,
          390.04,
          389.73,
          391.12,
          391.61,
          392.42,
          393.25,
          391.69,
          391.58,
          391.04,
          390.64,
          390.85,
          390.68,
          390.85,
          391.71,
          392.36,
          392.78,
          392.21,
          392.45,
          392.77,
          392.21,
          392.45,
          392.11,
          392.27,
          391.07,
          391.08,
          391.45,
          391.87,
          392.23,
          392.15,
          391.96,
          392.09,
          392.78,
          392.64,
          392.98,
          392.65,
          392.1,
          392.65,
          392.92,
          392.79,
          393.22,
          392.84,
          392.91,
          392.86,
          391.82,
          391.95,
          391.82,
          392.31,
          391.89,
          391.33,
          391.04,
          391.5,
          391.77,
          392.09,
          392.27,
          392.71,
          393.39,
          392.93,
          392.87,
          392.97,
          392.46
        ]
      },
      "ts": 1776721495.584288
    },
    "TSLA:5d": {
      "data": {
        "dates": [
          "04/14",
          "04/15",
          "04/16",
          "04/17",
          "04/20"
        ],
        "prices": [
          364.2,
          391.95,
          388.9,
          400.62,
          392.5
        ]
      },
      "ts": 1776721496.0241268
    },
    "TSLA:1mo": {
      "data": {
        "dates": [
          "03/23",
          "03/24",
          "03/25",
          "03/26",
          "03/27",
          "03/30",
          "03/31",
          "04/01",
          "04/02",
          "04/06",
          "04/07",
          "04/08",
          "04/09",
          "04/10",
          "04/13",
          "04/14",
          "04/15",
          "04/16",
          "04/17",
          "04/20"
        ],
        "prices": [
          380.85,
          383.03,
          385.95,
          372.11,
          361.83,
          355.28,
          371.75,
          381.26,
          360.59,
          352.82,
          346.65,
          343.25,
          345.62,
          348.95,
          352.42,
          364.2,
          391.95,
          388.9,
          400.62,
          392.5
        ]
      },
      "ts": 1776721496.4294744
    },
    "TSM:1d": {
      "data": {
        "dates": [
          "09:30",
          "09:35",
          "09:40",
          "09:45",
          "09:50",
          "09:55",
          "10:00",
          "10:05",
          "10:10",
          "10:15",
          "10:20",
          "10:25",
          "10:30",
          "10:35",
          "10:40",
          "10:45",
          "10:50",
          "10:55",
          "11:00",
          "11:05",
          "11:10",
          "11:15",
          "11:20",
          "11:25",
          "11:30",
          "11:35",
          "11:40",
          "11:45",
          "11:50",
          "11:55",
          "12:00",
          "12:05",
          "12:10",
          "12:15",
          "12:20",
          "12:25",
          "12:30",
          "12:35",
          "12:40",
          "12:45",
          "12:50",
          "12:55",
          "13:00",
          "13:05",
          "13:10",
          "13:15",
          "13:20",
          "13:25",
          "13:30",
          "13:35",
          "13:40",
          "13:45",
          "13:50",
          "13:55",
          "14:00",
          "14:05",
          "14:10",
          "14:15",
          "14:20",
          "14:25",
          "14:30",
          "14:35",
          "14:40",
          "14:45",
          "14:50",
          "14:55",
          "15:00",
          "15:05",
          "15:10",
          "15:15",
          "15:20",
          "15:25",
          "15:30",
          "15:35",
          "15:40",
          "15:45",
          "15:50",
          "15:55"
        ],
        "prices": [
          367.31,
          367.16,
          367.27,
          366.58,
          367.3,
          368.46,
          368.51,
          369.91,
          369.04,
          368.59,
          369.1,
          368.66,
          368.77,
          368.43,
          367.55,
          367.96,
          366.81,
          366.11,
          365.44,
          364.82,
          365.79,
          366.29,
          367.36,
          367.12,
          366.76,
          366.76,
          366.55,
          366.92,
          367.12,
          367.44,
          367.39,
          367.57,
          367.11,
          367.2,
          367.44,
          367.31,
          367.1,
          366.76,
          367.0,
          367.72,
          367.85,
          367.29,
          367.15,
          367.25,
          367.15,
          367.51,
          367.51,
          367.3,
          367.51,
          367.71,
          367.88,
          368.32,
          368.25,
          367.7,
          367.79,
          368.11,
          367.93,
          367.85,
          367.82,
          367.82,
          367.47,
          366.67,
          366.73,
          367.03,
          366.98,
          367.11,
          367.18,
          367.29,
          367.16,
          366.98,
          366.99,
          366.85,
          366.51,
          366.46,
          366.59,
          366.33,
          366.34,
          366.29
        ]
      },
      "ts": 1776721496.8184428
    },
    "TSM:5d": {
      "data": {
        "dates": [
          "04/14",
          "04/15",
          "04/16",
          "04/17",
          "04/20"
        ],
        "prices": [
          379.89,
          375.1,
          363.35,
          370.5,
          366.24
        ]
      },
      "ts": 1776721497.1828387
    },
    "TSM:1mo": {
      "data": {
        "dates": [
          "03/23",
          "03/24",
          "03/25",
          "03/26",
          "03/27",
          "03/30",
          "03/31",
          "04/01",
          "04/02",
          "04/06",
          "04/07",
          "04/08",
          "04/09",
          "04/10",
          "04/13",
          "04/14",
          "04/15",
          "04/16",
          "04/17",
          "04/20"
        ],
        "prices": [
          338.45,
          343.25,
          347.75,
          326.11,
          326.74,
          316.5,
          337.95,
          341.49,
          339.04,
          341.76,
          345.32,
          365.9,
          365.49,
          370.6,
          369.57,
          379.89,
          375.1,
          363.35,
          370.5,
          366.24
        ]
      },
      "ts": 1776721497.6155226
    },
    "VOO:1d": {
      "data": {
        "dates": [
          "09:30",
          "09:35",
          "09:40",
          "09:45",
          "09:50",
          "09:55",
          "10:00",
          "10:05",
          "10:10",
          "10:15",
          "10:20",
          "10:25",
          "10:30",
          "10:35",
          "10:40",
          "10:45",
          "10:50",
          "10:55",
          "11:00",
          "11:05",
          "11:10",
          "11:15",
          "11:20",
          "11:25",
          "11:30",
          "11:35",
          "11:40",
          "11:45",
          "11:50",
          "11:55",
          "12:00",
          "12:05",
          "12:10",
          "12:15",
          "12:20",
          "12:25",
          "12:30",
          "12:35",
          "12:40",
          "12:45",
          "12:50",
          "12:55",
          "13:00",
          "13:05",
          "13:10",
          "13:15",
          "13:20",
          "13:25",
          "13:30",
          "13:35",
          "13:40",
          "13:45",
          "13:50",
          "13:55",
          "14:00",
          "14:05",
          "14:10",
          "14:15",
          "14:20",
          "14:25",
          "14:30",
          "14:35",
          "14:40",
          "14:45",
          "14:50",
          "14:55",
          "15:00",
          "15:05",
          "15:10",
          "15:15",
          "15:20",
          "15:25",
          "15:30",
          "15:35",
          "15:40",
          "15:45",
          "15:50",
          "15:55"
        ],
        "prices": [
          651.9,
          651.4,
          651.61,
          651.43,
          652.11,
          652.41,
          651.95,
          652.16,
          652.01,
          651.84,
          652.27,
          651.73,
          651.47,
          651.35,
          651.0,
          651.49,
          650.7,
          650.06,
          649.67,
          649.53,
          649.73,
          649.93,
          650.55,
          651.12,
          650.44,
          650.55,
          650.45,
          650.42,
          650.42,
          650.54,
          650.1,
          650.41,
          650.51,
          650.49,
          650.53,
          650.58,
          650.83,
          650.49,
          650.6,
          650.64,
          650.65,
          650.55,
          650.39,
          650.7,
          650.93,
          651.16,
          651.12,
          650.85,
          650.56,
          650.78,
          650.85,
          650.89,
          650.93,
          650.64,
          650.65,
          651.06,
          651.07,
          651.27,
          651.42,
          651.19,
          651.18,
          650.83,
          651.01,
          651.2,
          651.41,
          651.15,
          651.12,
          651.28,
          651.3,
          651.18,
          651.03,
          650.92,
          650.71,
          650.81,
          650.62,
          650.79,
          650.91,
          651.51
        ]
      },
      "ts": 1776721497.9848223
    },
    "VOO:5d": {
      "data": {
        "dates": [
          "04/14",
          "04/15",
          "04/16",
          "04/17",
          "04/20"
        ],
        "prices": [
          638.35,
          643.45,
          644.86,
          652.78,
          651.54
        ]
      },
      "ts": 1776721498.3376281
    },
    "VOO:1mo": {
      "data": {
        "dates": [
          "03/23",
          "03/24",
          "03/25",
          "03/26",
          "03/27",
          "03/30",
          "03/31",
          "04/01",
          "04/02",
          "04/06",
          "04/07",
          "04/08",
          "04/09",
          "04/10",
          "04/13",
          "04/14",
          "04/15",
          "04/16",
          "04/17",
          "04/20"
        ],
        "prices": [
          602.53,
          600.48,
          603.75,
          593.05,
          582.96,
          580.93,
          597.55,
          602.3,
          602.99,
          605.67,
          606.04,
          621.34,
          625.02,
          624.6,
          630.72,
          638.35,
          643.45,
          644.86,
          652.78,
          651.54
        ]
      },
      "ts": 1776721498.7229893
    }
  },
  "symbols": [
    "2330.TW",
    "AAPL",
    "AMD",
    "AMZN",
    "AVGO",
    "GOOGL",
    "META",
    "MSFT",
    "NVDA",
    "ONDS",
    "OPEN",
    "QQQ",
    "TSLA",
    "TSM",
    "VOO"
  ],
  "last_refresh": 1776721481.9719832
}